rajaongkir_python_sdk/__init__.py
rajaongkir_python_sdk/client.py
rajaongkir_python_sdk/const.py
rajaongkir_python_sdk/decorator.py
rajaongkir_python_sdk/exception.py
rajaongkir_python_sdk/schema.py
rajaongkir_python_sdk-0.1.1.dist-info/METADATA
rajaongkir_python_sdk-0.1.1.dist-info/WHEEL
rajaongkir_python_sdk-0.1.1.dist-info/licenses/LICENSE
rajaongkir_python_sdk-0.1.1.dist-info/RECORD
