Metadata-Version: 2.3
Name: rajaongkir-python-sdk
Version: 0.1.1
Summary: this is python library for support RajaOngkir API
Project-URL: Repository, https://github.com/wihlarkop/rajaongkir-py
Project-URL: Issues, https://github.com/wihlarkop/rajaongkir-py/issues
Author-email: Wihlarko Prasdegdho <wihlarko26@gmail.com>
License: MIT License
License-File: LICENSE
Keywords: raja_ongkir,rajaongkir,rajaongkir python sdk
Classifier: Development Status :: 3 - Alpha
Classifier: Intended Audience :: Developers
Classifier: License :: OSI Approved :: MIT License
Classifier: Programming Language :: Python :: 3 :: Only
Classifier: Programming Language :: Python :: 3.11
Classifier: Programming Language :: Python :: 3.12
Classifier: Topic :: Software Development :: Build Tools
Requires-Python: >=3.11
Requires-Dist: httpx>=0.27.2
Requires-Dist: pydantic>=2.9.2
